{
  "oneOf": [
    {
      "type": "object",
      "properties": {
        "name": {
          "type": "string",
          "title": "Name",
          "description": "Vollständiger Name"
        }
      },
      "required": [
        "name"
      ],
      "title": "Mensch",
      "description": "Natürliche Person mit Name"
    },
    {
      "type": "object",
      "properties": {
        "nummer": {
          "type": "string",
          "title": "Nummer",
          "description": "Serien- oder Inventarnummer"
        }
      },
      "required": [
        "nummer"
      ],
      "title": "Maschine",
      "description": "Technisches Gerät mit Seriennummer"
    }
  ],
  "title": "Person",
  "description": "Wähle zwischen Mensch und Maschine"
}
